CHANGES.txt
LICENSE
MANIFEST.in
README.rst
dev_requirements.txt
requirements.txt
sample_client.py
sample_server.py
setup.py
PyHawk.egg-info/PKG-INFO
PyHawk.egg-info/SOURCES.txt
PyHawk.egg-info/dependency_links.txt
PyHawk.egg-info/not-zip-safe
PyHawk.egg-info/requires.txt
PyHawk.egg-info/top_level.txt
hawk/__init__.py
hawk/client.py
hawk/hcrypto.py
hawk/server.py
hawk/util.py