Metadata-Version: 1.0
Name: PyHawk
Version: 0.1.1
Summary: Python Libraries for HAWK
